LICENSE.txt
MANIFEST.in
README.rst
setup.py
src/django_editos.egg-info/PKG-INFO
src/django_editos.egg-info/SOURCES.txt
src/django_editos.egg-info/dependency_links.txt
src/django_editos.egg-info/namespace_packages.txt
src/django_editos.egg-info/requires.txt
src/django_editos.egg-info/top_level.txt
src/geelweb/__init__.py
src/geelweb/django/__init__.py
src/geelweb/django/editos/__init__.py
src/geelweb/django/editos/admin.py
src/geelweb/django/editos/models.py
src/geelweb/django/editos/settings.py
src/geelweb/django/editos/tests.py
src/geelweb/django/editos/migrations/0001_initial.py
src/geelweb/django/editos/migrations/__init__.py
src/geelweb/django/editos/south_migrations/0001_initial.py
src/geelweb/django/editos/south_migrations/0002_auto__add_field_edito_button_label__add_field_edito_date_created__add_.py
src/geelweb/django/editos/south_migrations/__init__.py
src/geelweb/django/editos/templates/editos/carousel.html
src/geelweb/django/editos/templatetags/__init__.py
src/geelweb/django/editos/templatetags/editos.py