Metadata-Version: 1.1
Name: django-editos
Version: 1.4.1
Summary: Django app to manage and display editos
Home-page: https://github.com/geelweb/django-editos
Author: Guillaume Luchet
Author-email: <guillaume@geelweb.org>
License: MIT
Download-URL: https://github.com/geelweb/django-editos/tarball/1.4.1
Keywords: django,editos,carousel
Platform: UNKNOWN
